swh/counters/__init__.py
swh/counters/cli.py
swh/counters/history.py
swh/counters/in_memory.py
swh/counters/interface.py
swh/counters/journal_client.py
swh/counters/kafka_client.py
swh/counters/py.typed
swh/counters/redis.py
swh/counters/api/__init__.py
swh/counters/api/client.py
swh/counters/api/server.py
swh/counters/tests/__init__.py
swh/counters/tests/conftest.py
swh/counters/tests/test_cli.py
swh/counters/tests/test_history.py
swh/counters/tests/test_init.py
swh/counters/tests/test_inmemory.py
swh/counters/tests/test_journal_client.py
swh/counters/tests/test_redis.py
swh/counters/tests/test_server.py
swh/counters/tests/data/content.json
swh/counters/tests/data/foo.json
swh/counters/tests/data/revision.json
swh_counters-0.12.0.dist-info/licenses/AUTHORS
swh_counters-0.12.0.dist-info/licenses/LICENSE
swh_counters-0.12.0.dist-info/METADATA
swh_counters-0.12.0.dist-info/WHEEL
swh_counters-0.12.0.dist-info/entry_points.txt
swh_counters-0.12.0.dist-info/top_level.txt
swh_counters-0.12.0.dist-info/RECORD
